streamlit_observable/__init__.py
streamlit_observable/showcase.py
streamlit_observable/frontend/build/asset-manifest.json
streamlit_observable/frontend/build/index.html
streamlit_observable/frontend/build/precache-manifest.5b46dc2e487fd2207c85c30b7c977719.js
streamlit_observable/frontend/build/service-worker.js
streamlit_observable/frontend/build/static/js/2.dad34968.chunk.js
streamlit_observable/frontend/build/static/js/2.dad34968.chunk.js.LICENSE.txt
streamlit_observable/frontend/build/static/js/2.dad34968.chunk.js.map
streamlit_observable/frontend/build/static/js/main.5599c993.chunk.js
streamlit_observable/frontend/build/static/js/main.5599c993.chunk.js.LICENSE.txt
streamlit_observable/frontend/build/static/js/main.5599c993.chunk.js.map
streamlit_observable/frontend/build/static/js/runtime-main.11ec9aca.js
streamlit_observable/frontend/build/static/js/runtime-main.11ec9aca.js.map
streamlit_observable-0.0.8.dist-info/LICENSE
streamlit_observable-0.0.8.dist-info/METADATA
streamlit_observable-0.0.8.dist-info/WHEEL
streamlit_observable-0.0.8.dist-info/top_level.txt
streamlit_observable-0.0.8.dist-info/RECORD
