Metadata-Version: 2.1
Name: streamlit-observable
Version: 0.0.8
Summary: A Streamlit component for embedding Observable notebooks in Streamlit Apps
Home-page: https://github.com/asg017/streamlit-observable
Author: Alex Garcia
Author-email: alexsebastian.garcia@gmail.com
License: UNKNOWN
Platform: UNKNOWN
Requires-Python: >=3.6
